rxn_insight/__about__.py
rxn_insight/__init__.py
rxn_insight/classification.py
rxn_insight/database.py
rxn_insight/molecule.py
rxn_insight/ord.py
rxn_insight/reaction.py
rxn_insight/representation.py
rxn_insight/utils.py
rxn_insight/data/chem21.csv
rxn_insight/data/functional_groups.json
rxn_insight/data/pricelist_10g.csv
rxn_insight/data/smirks.json
rxn_insight-0.1.2.dist-info/METADATA
rxn_insight-0.1.2.dist-info/WHEEL
rxn_insight-0.1.2.dist-info/licenses/LICENSE
rxn_insight-0.1.2.dist-info/RECORD
