Metadata-Version: 2.4
Name: rxn-insight
Version: 0.1.2
Summary: RXN insight package
Project-URL: source, https://github.com/mrodobbe/rxn-insight
Project-URL: tracker, https://github.com/mrodobbe/rxn-insight/issues
Project-URL: documentation, https://rxn-insight.readthedocs.io
Author-email: "Maarten R. Dobbelaere" <mrodobbe.dobbelaere@ugent.be>
License: MIT License
License-File: LICENSE
Classifier: Development Status :: 3 - Alpha
Classifier: Intended Audience :: Developers
Classifier: License :: OSI Approved :: MIT License
Classifier: Operating System :: OS Independent
Classifier: Programming Language :: Python
Classifier: Programming Language :: Python :: 3
Classifier: Programming Language :: Python :: 3.8
Classifier: Programming Language :: Python :: 3.9
Classifier: Programming Language :: Python :: 3.10
Classifier: Programming Language :: Python :: 3.11
Requires-Python: >=3.8
Requires-Dist: ipykernel
Requires-Dist: numpy<=1.26.4
Requires-Dist: openpyxl
Requires-Dist: pandas
Requires-Dist: pyarrow>=15.0.2
Requires-Dist: rdchiral>=1.1.0
Requires-Dist: rdkit
Requires-Dist: rxnmapper>=0.3.0
Requires-Dist: sphinx-rtd-theme
Requires-Dist: sphinxcontrib-bibtex
Requires-Dist: tqdm
Provides-Extra: doc
Requires-Dist: furo; extra == 'doc'
Requires-Dist: myst-parser; extra == 'doc'
Requires-Dist: sphinx-book-theme; extra == 'doc'
Requires-Dist: sphinx-copybutton; extra == 'doc'
Requires-Dist: sphinx-rtd-theme; extra == 'doc'
Requires-Dist: sphinx>=5; extra == 'doc'
Provides-Extra: test
Requires-Dist: genbadge[coverage]; extra == 'test'
Requires-Dist: hypothesis; extra == 'test'
Requires-Dist: mypy; extra == 'test'
Requires-Dist: pytest; extra == 'test'
Requires-Dist: pytest-cov; extra == 'test'
Requires-Dist: tox; extra == 'test'
